{
    "songs": [
        {
            "title": "Roundabout",
            "artist": "Yes",
            "album": "Fragile",
            "year": "1972"
        },
        {
            "title": "Cans and Brahms",
            "artist": "Yes",
            "album": "Fragile",
            "year": "1972"
        },
        {
            "title": "We Have Heaven",
            "artist": "Yes",
            "album": "Fragile",
            "year": "1972"
        },
        {
            "title": "South Side of the Sky",
            "artist": "Yes",
            "album": "Fragile",
            "year": "1972"
        },
        {
            "title": "Five Percent for Nothing",
            "artist": "Yes",
            "album": "Fragile",
            "year": "1972"
        },
        {
            "title": "Long Distance Runaround",
            "artist": "Yes",
            "album": "Fragile",
            "year": "1972"
        },
        {
            "title": "The Fish (Schindleria Praematurus)",
            "artist": "Yes",
            "album": "Fragile",
            "year": "1972"
        },
        {
            "title": "Mood for a Day",
            "artist": "Yes",
            "album": "Fragile",
            "year": "1972"
        },
        {
            "title": "Heart of the Sunrise",
            "artist": "Yes",
            "album": "Fragile",
            "year": "1972"
        }
    ]
}